{"id":176516760,"name":"Beyaz Erkek Basic Regular Fit Bisiklet Yaka K\u0131sa Kollu T-Shirt TMNSS22TS0271","link":"\/trendyol-man\/beyaz-erkek-basic-regular-fit-bisiklet-yaka-kisa-kollu-t-shirt-tmnss22ts0271-p-176516760","images":["https:\/\/cdn.dsmcdn.com\/ty296\/product\/media\/images\/20220115\/11\/26863935\/287606879\/2\/2_org_zoom.jpg","https:\/\/cdn.dsmcdn.com\/ty295\/product\/media\/images\/20220115\/11\/26863935\/287606879\/3\/3_org_zoom.jpg","https:\/\/cdn.dsmcdn.com\/ty294\/product\/media\/images\/20220115\/11\/26863935\/287606879\/4\/4_org_zoom.jpg","https:\/\/cdn.dsmcdn.com\/ty294\/product\/media\/images\/20220115\/11\/26863935\/287606879\/6\/6_org_zoom.jpg","https:\/\/cdn.dsmcdn.com\/ty294\/product\/media\/images\/20220115\/11\/26863935\/287606879\/5\/5_org_zoom.jpg","https:\/\/cdn.dsmcdn.com\/ty407\/product\/media\/images\/20220420\/21\/95526358\/287606879\/2\/2_org_zoom.jpg","https:\/\/cdn.dsmcdn.com\/ty407\/product\/media\/images\/20220420\/21\/95526358\/287606879\/3\/3_org_zoom.jpg","https:\/\/cdn.dsmcdn.com\/ty406\/product\/media\/images\/20220420\/21\/95526358\/287606879\/4\/4_org_zoom.jpg"],"price":{"profitMargin":0,"discountedPrice":{"text":"62,99 TL","value":62.99},"sellingPrice":{"text":"89,99 TL","value":89.99},"originalPrice":{"text":"64,99 TL","value":64.99},"currency":"TRY"},"rating":4.36,"campaign":"Trendyol","brand":{"id":103500,"name":"TRENDYOL MAN","slug":"trendyol-man"},"category":{"id":604,"name":"T-Shirt","slug":"t-shirt"},"showColor":"Beyaz","showSize":"S","sizes":[{"value":"S","inStock":true,"price":62.99,"currency":"TRY"},{"value":"M","inStock":true,"price":62.99,"currency":"TRY"},{"value":"L","inStock":true,"price":62.99,"currency":"TRY"},{"value":"XL","inStock":true,"price":62.99,"currency":"TRY"},{"value":"2XL","inStock":true,"price":62.99,"currency":"TRY"},{"value":"3XL","inStock":false,"price":62.99,"currency":"TRY"}],"description":"Mankenin \u00fczerindeki \u00fcr\u00fcn M bedendir.\nModelin \u00d6l\u00e7\u00fcleri: Boy: 1.88, G\u00f6\u011f\u00fcs: 98 Bel: 75, Kal\u00e7a: 99\n%66 Polyester %34 Pamuk\nRegular Fit: Rahat, v\u00fccudu sarmayan bir kesimdir. Kal\u0131p olarak slim fite g\u00f6re biraz daha bolluk pay\u0131 vard\u0131r.\nKonsept \u00e7ekimlerinde renkler \u0131\u015f\u0131k farkl\u0131l\u0131\u011f\u0131ndan dolay\u0131 de\u011fi\u015fiklik g\u00f6sterebilir.\nBu \u00fcr\u00fcnden en fazla 10 adet sipari\u015f verilebilir. 10 adetin \u00fczerindeki sipari\u015fleri Trendyol iptal etme hakk\u0131n\u0131 sakl\u0131 tutar.\nKampanya fiyat\u0131ndan sat\u0131lmak \u00fczere 100 adetten fazla stok sunulmu\u015ftur.\nListelenen fiyat 18 Haziran 2022 tarihine kadar ge\u00e7erlidir.\nBir \u00fcr\u00fcn, birden fazla sat\u0131c\u0131 taraf\u0131ndan sat\u0131labilir. Birden fazla sat\u0131c\u0131 taraf\u0131ndan sat\u0131\u015fa sunulan \u00fcr\u00fcnlerin sat\u0131c\u0131lar\u0131 \u00fcr\u00fcn i\u00e7in belirledikleri fiyata, sat\u0131c\u0131 puanlar\u0131na, teslimat stat\u00fclerine, \u00fcr\u00fcnlerdeki promosyonlara, kargonun bedava olup olmamas\u0131na ve \u00fcr\u00fcnlerin h\u0131zl\u0131 teslimat ile teslim edilip edilememesine, \u00fcr\u00fcnlerin stok ve kategorileri bilgilerine g\u00f6re s\u0131ralanmaktad\u0131r.\n\u00dcr\u00fcnlerimiz TRENDYOL etiketi ile g\u00f6nderilecektir.","reviews":[{"user":"**** ****","rate":5,"comment":"gayet kaliteli bir ti\u015f\u00f6rt indirimdeyken ald\u0131m.","date":"8 May\u0131s 2022"},{"user":"E** D**","rate":5,"comment":"Tam bir fiyat performans \u00fcr\u00fcn\u00fc indirimdeyken al\u0131nmal\u0131","date":"23 May\u0131s 2022"},{"user":"D** K**","rate":5,"comment":"indirimde guzel fiyata almistim ty urunleri zaten kaliteli indirimde kacirmayin","date":"27 Nisan 2022"},{"user":"**** ****","rate":5,"comment":"\u00c7ok g\u00fczel  te\u015fekk\u00fcrler","date":"9 Haziran 2022"},{"user":"A** K**","rate":5,"comment":"\u00dcr\u00fcn\u00fc be\u011fendim","date":"29 May\u0131s 2022"},{"user":"M** G**","rate":5,"comment":"cok guzel.","date":"27 May\u0131s 2022"},{"user":"m** a**","rate":4,"comment":"kesinlikle alinir","date":"21 May\u0131s 2022"},{"user":"D** c** K**","rate":5,"comment":"G\u00fczel kullan\u0131\u015fl\u0131","date":"18 May\u0131s 2022"},{"user":"c** D**","rate":5,"comment":"Babam i\u00e7in alm\u0131\u015ft\u0131m  kalitesi kargolama iyiydi","date":"28 May\u0131s 2022"},{"user":"E** K**","rate":5,"comment":"\u00c7ok be\u011fendi karde\u015fime alm\u0131\u015ft\u0131m","date":"24 May\u0131s 2022"},{"user":"S** K**","rate":5,"comment":"\u00fcr\u00fcn g\u00fczel","date":"8 Haziran 2022"},{"user":"**** ****","rate":5,"comment":"kuzenime alm\u0131\u015ft\u0131m yumu\u015fac\u0131k ve kaliteli marka muadili gibi teredd\u00fct etmeden alabilirsiniz \ud83d\ude07","date":"4 May\u0131s 2022"},{"user":"M** M**","rate":5,"comment":"G\u00fczel \u00fcr\u00fcn sevdim","date":"11 May\u0131s 2022"},{"user":"**** ****","rate":5,"comment":"g\u00fczel \u00fcr\u00fcn be\u011fendim","date":"25 Nisan 2022"},{"user":"N** K** S**","rate":5,"comment":"kampanya zaman\u0131nda ald\u0131m uyguna geldi. kampanya olmad\u0131\u011f\u0131 s\u00fcrece Trendyol markal\u0131 \u00fcr\u00fcnleri alm\u0131yorum","date":"29 May\u0131s 2022"},{"user":"\u0130** V**","rate":5,"comment":"Can\u0131m sevgilime ald\u0131m, bej g\u00f6mlekle \u00e7ok yak\u0131\u015ft\u0131 \ud83e\udd0d","date":"11 Haziran 2022"},{"user":"B** K**","rate":5,"comment":"Penyesi \u00e7ok iyi","date":"30 May\u0131s 2022"},{"user":"Ahmet k.","rate":5,"comment":"kaliteli G\u00fczel \u00fcr\u00fcn","date":"29 May\u0131s 2022"},{"user":"**** ****","rate":5,"comment":"G\u00fczel bir \u00fcr\u00fcn","date":"23 May\u0131s 2022"},{"user":"S** Y**","rate":5,"comment":"Kaliteli ve g\u00fczel \ud83d\udc4d","date":"16 May\u0131s 2022"},{"user":"B** \u00c7**","rate":5,"comment":"\u00c7ok \u00e7ok be\u011fendik","date":"12 May\u0131s 2022"},{"user":"M** F** \u0130**","rate":5,"comment":"\u00e7ok g\u00fczel bir \u00fcr\u00fcn","date":"10 May\u0131s 2022"},{"user":"E** A**","rate":2,"comment":"Eh diyebilirim  ancak","date":"6 May\u0131s 2022"},{"user":"G** \u015e**","rate":5,"comment":"\u00c7ok kaliteli","date":"4 May\u0131s 2022"},{"user":"E** T**","rate":5,"comment":"Ba\u015far\u0131l\u0131 Bi \u00fcr\u00fcn","date":"28 Nisan 2022"},{"user":"s** t**","rate":5,"comment":"Gayet g\u00fczel","date":"26 Nisan 2022"},{"user":"Y** C** A**","rate":5,"comment":"Kaliteli be\u011fendim","date":"26 Nisan 2022"},{"user":"M** A** K**","rate":5,"comment":"g\u00fczel iyi very good","date":"22 Nisan 2022"},{"user":"Zeynep i.","rate":5,"comment":"muhte\u015fem kesinlikle tavsiye ederim","date":"20 Nisan 2022"},{"user":"C** \u00c7**","rate":5,"comment":"kaliteli te\u015fekk\u00fcrler","date":"17 Nisan 2022"},{"user":"N** T**","rate":5,"comment":"G\u00fczel e\u015fime yak\u0131\u015ft\u0131","date":"29 May\u0131s 2022"},{"user":"n** g**","rate":5,"comment":"Harika \u00fcr\u00fcn","date":"11 May\u0131s 2022"},{"user":"s** \u00e7**","rate":5,"comment":"\u00c7ok g\u00fczel","date":"30 Nisan 2022"},{"user":"B** \u015e**","rate":5,"comment":"\u00c7ok g\u00fczell \u00e7ok be\u011fendimm","date":"30 Nisan 2022"},{"user":"E** K**","rate":5,"comment":"te\u015fekk\u00fcrler g\u00fczel \u00fcr\u00fcn","date":"21 Nisan 2022"},{"user":"F** D**","rate":5,"comment":"\u00e7ok be\u011fendim","date":"15 Nisan 2022"},{"user":"Mahmut B.","rate":1,"comment":"be\u011fenmedim","date":"14 Nisan 2022"},{"user":"t** k** u**","rate":5,"comment":"selam \u00e7ok kaliteli","date":"12 Nisan 2022"},{"user":"salih d.","rate":5,"comment":"\u00fcr\u00fcn \u00e7ok g\u00fczel bekledi\u011fimden daha iyi te\u015fekkurler","date":"11 Nisan 2022"},{"user":"**** ****","rate":5,"comment":"\u00e7ok memnun kald\u0131m","date":"10 Nisan 2022"},{"user":"**** ****","rate":5,"comment":"gayet g\u00fczel","date":"5 Nisan 2022"},{"user":"D** O**","rate":5,"comment":"E\u015fim i\u00e7in ald\u0131m ve \u00e7ok g\u00fczel oldu kalitesi \u00e7ok g\u00fczel","date":"18 Nisan 2022"},{"user":"B** \u015e**","rate":4,"comment":"kuma\u015f\u0131ni pek be\u011fenmedim ama giyilir","date":"5 Haziran 2022"},{"user":"m** n** \u00f6**","rate":5,"comment":"E\u015fime ald\u0131m \u00e7ok be\u011fendi","date":"30 Nisan 2022"},{"user":"H** \u00c7**","rate":5,"comment":"likral\u0131 yumu\u015fak kaliteli penyesi var \ud83d\udc4d","date":"9 May\u0131s 2022"},{"user":"Mehmet D.","rate":5,"comment":"\u00fcr\u00fcn\u00fc be\u011fendim. g\u00f6be\u011fi olan M giyenler, L al\u0131rlarsa \u00e7ok daha iyi olacakt\u0131r..","date":"2 May\u0131s 2022"},{"user":"B** T** \u0130**","rate":5,"comment":"E\u015fime ald\u0131m be\u011fendi tam oldu te\u015fekk\u00fcrler","date":"30 May\u0131s 2022"},{"user":"H** \u00dc**","rate":5,"comment":"E\u015fime ald\u0131m be\u011fendik \ud83d\udc4d","date":"17 May\u0131s 2022"},{"user":"M** t**","rate":5,"comment":"tam oldu be\u011fendim","date":"13 May\u0131s 2022"},{"user":"\u00d6** I** T**","rate":5,"comment":"E\u015fime ve abime ald\u0131m severek kullan\u0131yorlar.","date":"9 May\u0131s 2022"},{"user":"Mert A.","rate":5,"comment":"ger\u00e7ekten kaliteli bir \u00fcr\u00fcn pamuk oldu\u011funu her dokusunu belli ediyor kalite oldu\u011funu hissetiyor herkese tavsiye ederim Trendyol ekibine \u00e7ok te\u015fekk\u00fcr ederim","date":"9 Haziran 2022"},{"user":"**** ****","rate":5,"comment":"m\u00fckemmel kalitesi ve dokusu var te\u015fekk\u00fcrler \ud83c\udf3b","date":"29 Nisan 2022"},{"user":"**** ****","rate":5,"comment":"\u00fcr\u00fcnleri \u00e7ok b\u011fndk sornsuz gldi","date":"17 May\u0131s 2022"},{"user":"E** \u00d6**","rate":5,"comment":"Sportif , v\u00fccuda g\u00fczel oturan kaliteli bir \u00fcr\u00fcn tavsiye ederim","date":"3 May\u0131s 2022"},{"user":"H** T**","rate":5,"comment":"Gayet g\u00fczel ve rahat.","date":"6 May\u0131s 2022"},{"user":"k** f**","rate":5,"comment":"gayet \u015f\u0131k ve rahat","date":"27 Nisan 2022"},{"user":"Z** S**","rate":4,"comment":"Karde\u015fime alm\u0131\u015ft\u0131m, dokusu duru\u015fu gayet g\u00fczel","date":"27 Nisan 2022"},{"user":"r** i**","rate":5,"comment":"\u00e7ok h\u0131zl\u0131 geldi \u00fcr\u00fcn\u00fcn kalitesi g\u00fczel","date":"19 Nisan 2022"},{"user":"Harun E.","rate":4,"comment":"Her Trendyol sipari\u015finde sepete ekledi\u011fim bir \u00fcr\u00fcn oldu. Gayet iyi bir \u00fcr\u00fcn, fiyat performans\u0131 \u00e7ok \u00e7ok iyi.","date":"17 May\u0131s 2022"},{"user":"G\u00f6kay K.","rate":5,"comment":"Paras\u0131na g\u00f6re \u00e7ok iyi tavsiye ediyorum","date":"27 Nisan 2022"},{"user":"\u015e** U**","rate":5,"comment":"Tiri\u015f tiril tavsiye ederim lacivertinide ald\u0131m ben","date":"6 Nisan 2022"},{"user":"M** Y**","rate":5,"comment":"182\/78 M tam","date":"26 Nisan 2022"},{"user":"H** G**","rate":5,"comment":"Rahat ve kaliteli Te\u015fekk\u00fcrler.","date":"26 Nisan 2022"},{"user":"A** K**","rate":5,"comment":"Sevgilime ald\u0131m \u00e7ok yak\u0131\u015ft\u0131","date":"12 May\u0131s 2022"},{"user":"m** k**","rate":5,"comment":"Gayet g\u00fczel ve \u015f\u0131k;)","date":"24 Mart 2022"},{"user":"**** ****","rate":5,"comment":"kaliteli \u00fcr\u00fcn","date":"11 Mart 2022"},{"user":"O** \u00c7**","rate":3,"comment":"kaliteli gibi","date":"11 Mart 2022"},{"user":"Samet G.","rate":5,"comment":"ba\u015far\u0131l\u0131","date":"8 Mart 2022"},{"user":"e** a**","rate":5,"comment":"harika bay\u0131ld\u0131m","date":"27 \u015eubat 2022"},{"user":"A** \u00c7**","rate":5,"comment":"\u00fcr\u00fcn g\u00fczel penyesi kaliteli fakat e\u015fime b\u00fcy\u00fck geldi kendi bedeni olmas\u0131na ra\u011fmen san\u0131r\u0131m kal\u0131plar\u0131 b\u00fcy\u00fck iade","date":"7 Haziran 2022"},{"user":"U** K**","rate":5,"comment":"Uygun fiyat g\u00fczel \u00fcr\u00fcn","date":"20 May\u0131s 2022"},{"user":"S** \u00c7**","rate":5,"comment":"g\u00fczel \u00fcr\u00fcn","date":"3 Mart 2022"},{"user":"t** e** \u00e7**","rate":5,"comment":"e\u015fim i\u00e7in ald\u0131m. \u00e7ok be\u011fendik","date":"24 Nisan 2022"},{"user":"**** ****","rate":5,"comment":"E\u015fim i\u00e7in alm\u0131\u015ft\u0131m. \u00c7ok be\u011fendi.","date":"5 Nisan 2022"},{"user":"M** A** \u00d6**","rate":5,"comment":"\ud83d\udc4d\ud83c\udffb\ud83d\udc4d\ud83c\udffb\ud83d\udc4d\ud83c\udffb\ud83d\udc4d\ud83c\udffb\ud83d\udc4d\ud83c\udffb\ud83d\udc4d\ud83c\udffb\ud83d\udc4d\ud83c\udffb\ud83d\udc4d\ud83c\udffb\ud83d\udc4d\ud83c\udffb\ud83d\udc4d\ud83c\udffb\ud83d\udc4d\ud83c\udffb","date":"29 Nisan 2022"},{"user":"s** k**","rate":1,"comment":"FAN\u0130LA gibi :(","date":"18 Nisan 2022"},{"user":"P** E** T**","rate":5,"comment":"Fiyat performans iyi","date":"30 Nisan 2022"},{"user":"**** ****","rate":5,"comment":"\u00c7ok iyi bu fiyata m\u00fckemmel","date":"26 Nisan 2022"},{"user":"mehmet n. g.","rate":5,"comment":"Tam Benlik uygun fiyatl\u0131 kaliteli \u00fcr\u00fcnler..Do\u011fru bir al\u0131\u015fveri\u015f yapt\u0131\u011f\u0131m\u0131 d\u00fc\u015f\u00fcn\u00fcyorum..","date":"23 Nisan 2022"},{"user":"b** k**","rate":5,"comment":"\u00e7ok g\u00fczel bu fiyata gayet iyi","date":"12 Nisan 2022"},{"user":"g** b**","rate":5,"comment":"f\/p guzel bir urun","date":"9 Nisan 2022"},{"user":"**** ****","rate":4,"comment":"Sorunsuz kargo sorunsuz \u00fcr\u00fcn","date":"18 May\u0131s 2022"},{"user":"H** \u00c7** K**","rate":5,"comment":"80 kilo L tam oluyor","date":"11 May\u0131s 2022"},{"user":"S** k**","rate":5,"comment":"BENDEN UYDU TE\u015eEK\u00dcR EDER\u0130M.","date":"17 Mart 2022"},{"user":"M** A**","rate":5,"comment":"Gayet g\u00fczel bir ti\u015f\u00f6rt. Yumu\u015fak dokuya sahip tavsiye ederim","date":"12 \u015eubat 2022"},{"user":"E** \u00d6** A**","rate":5,"comment":"dokusu yumu\u015fak ve tam kal\u0131p..","date":"22 Nisan 2022"},{"user":"mustafa d.","rate":1,"comment":"evde yatarken filan giyilir kalitesiz","date":"1 Nisan 2022"},{"user":"E** B**","rate":5,"comment":"indirimden ald\u0131m, g\u00fczel bir ti\u015f\u00f6rt ama indirimsiz fiyat\u0131na de\u011fmez","date":"27 \u015eubat 2022"},{"user":"B** S** \u00d6**","rate":5,"comment":"kaliteli \u00fcr\u00fcn ve hizli teslimat","date":"18 Nisan 2022"},{"user":"**** ****","rate":4,"comment":"Paketleme ve kalitesi g\u00fczel","date":"4 Mart 2022"},{"user":"**** ****","rate":5,"comment":"ger\u00e7ekten penyesi \u00e7ok g\u00fczel ayn\u0131s\u0131 geldi","date":"30 Nisan 2022"},{"user":"F** D**","rate":4,"comment":"tam bekledi\u011fim gibi geldi","date":"9 Nisan 2022"},{"user":"m** C**","rate":2,"comment":"g\u00f6r\u00fcnd\u00fc\u011f\u00fc kadar kaliteli gelmedi atlet penyesi kalitesinde","date":"16 Nisan 2022"},{"user":"Ali Y.","rate":5,"comment":"Kendim i\u00e7in ald\u0131m boy ve kiloya g\u00f6re al\u0131nmas\u0131n\u0131 tercih ederim istedi\u011fim gibi ula\u015ft\u0131","date":"12 May\u0131s 2022"},{"user":"**** ****","rate":4,"comment":"normal bir urun","date":"10 May\u0131s 2022"},{"user":"s** a**","rate":5,"comment":"basic olmas\u0131 hayat kurtar\u0131r","date":"9 Haziran 2022"},{"user":"**** ****","rate":5,"comment":"\u00fcr\u00fcn\u00fcn yeri yumu\u015fac\u0131k","date":"13 \u015eubat 2022"},{"user":"**** ****","rate":5,"comment":"Yeterli kalitede, fiyat performans basarili.","date":"24 Mart 2022"},{"user":"Z** Y** S**","rate":4,"comment":"Tam giy \u00e7\u0131k bir yazl\u0131k par\u00e7a fiyat\u0131 gayet uygun","date":"6 Nisan 2022"},{"user":"E** \u00d6**","rate":3,"comment":"be\u011fenmedim \u0130nce","date":"2 Haziran 2022"},{"user":"**** ****","rate":3,"comment":"Abime ald\u0131m idare eder","date":"26 May\u0131s 2022"},{"user":"**** ****","rate":5,"comment":"UCUZ KAL\u0130TE","date":"15 Nisan 2022"},{"user":"**** ****","rate":5,"comment":"kalitesi fakan baya iyi","date":"28 \u015eubat 2022"},{"user":"M** T**","rate":4,"comment":"G\u00fczel kaliteli","date":"21 \u015eubat 2022"},{"user":"O** T**","rate":5,"comment":"uygun ve kaliteli","date":"19 \u015eubat 2022"},{"user":"Y** k** A**","rate":5,"comment":"Harika doku hisayat\u0131 da g\u00fczel","date":"15 \u015eubat 2022"},{"user":"M** K**","rate":5,"comment":"\u00e7ok iyiiiiiii","date":"14 \u015eubat 2022"},{"user":"**** ****","rate":5,"comment":"\u00c7ok kaliteli","date":"10 \u015eubat 2022"},{"user":"A** Y**","rate":5,"comment":"cok guzel kaliteli","date":"5 \u015eubat 2022"},{"user":"M** \u00c7**","rate":5,"comment":"G\u00fczel be\u011fendik","date":"2 \u015eubat 2022"},{"user":"H** S**","rate":5,"comment":"g\u00fczel bur par\u00e7a","date":"23 Nisan 2022"},{"user":"d** s**","rate":2,"comment":"birinci y\u0131kamada topaklanma yapt\u0131 b\u00f6yle bir \u015fey nas\u0131l olabilir , pazardan ald\u0131\u011f\u0131m\u0131z atlet de\u011fil ki bu.","date":"8 May\u0131s 2022"},{"user":"U** Y**","rate":5,"comment":"Gayet g\u00fczel ho\u015fuma gitti kal\u0131b\u0131da g\u00fczel","date":"24 Nisan 2022"},{"user":"I\u015f\u0131l E.","rate":5,"comment":"kalitesini sevdim, hafif dokumlu duruyor.","date":"11 \u015eubat 2022"},{"user":"**** ****","rate":3,"comment":"Atlet gibi bi\u015fey","date":"12 \u015eubat 2022"},{"user":"y** e** d**","rate":5,"comment":"kal\u0131p \u00e7ok g\u00fczel.Kuma\u015f ise efsane te\u015fekk\u00fcrler tyman:)","date":"3 Haziran 2022"},{"user":"**** ****","rate":4,"comment":"Solgun bir beyaz ama iyi","date":"13 Nisan 2022"},{"user":"M** G**","rate":5,"comment":"\u00dcr\u00fcn \u00e7ok g\u00fczel","date":"22 Ocak 2022"},{"user":"D** \u00d6**","rate":1,"comment":"Hi\u00e7 be\u011fenmedik g\u00f6r\u00fcld\u00fc\u011f\u00fc gibi de\u011fil idaede ettik","date":"14 Nisan 2022"},{"user":"Hatice K.","rate":5,"comment":"Mavi ve bejinide ald\u0131m \u00e7ok g\u00fczel kuma\u015f\u0131 vs hediye ald\u0131m \u00e7ok be\u011fenildi kendi bedeninizi tercih edebilirsiniz","date":"7 Haziran 2022"},{"user":"Gamze P.","rate":1,"comment":"Vallahi \u015faka gibi nas\u0131l yanl\u0131\u015f \u00fcr\u00fcn yolluyorsunuz hayret","date":"16 May\u0131s 2022"},{"user":"M** K**","rate":5,"comment":"\u00fcr\u00fcn gayet g\u00fczel resimdeki gibi geldi \u00e7ok memnun kald\u0131m tavsiye ederim te\u015fekk\u00fcrler","date":"15 \u015eubat 2022"},{"user":"y** t**","rate":5,"comment":"tam kal\u0131p","date":"6 Nisan 2022"},{"user":"g** a**","rate":4,"comment":"bu fiyata g\u00f6re \u00e7ok iyi tavsiye ediyorum","date":"9 \u015eubat 2022"},{"user":"**** ****","rate":5,"comment":"Uygun fiyatl\u0131 g\u00fczel \u00fcr\u00fcn","date":"4 \u015eubat 2022"},{"user":"\u015f** c**","rate":4,"comment":"tshirtin alt taraf\u0131nda delik vard\u0131 defolu geldi","date":"10 Nisan 2022"},{"user":"\u015f** s** d**","rate":5,"comment":"Kal\u0131p olarak tam kal\u0131p e\u015fime aldim begendi","date":"20 Nisan 2022"},{"user":"B** B**","rate":5,"comment":"Fiyat performans \u00fcr\u00fcn\u00fc \u00e7ok beklentiye girmemek laz\u0131m","date":"20 Ocak 2022"},{"user":"G** Y**","rate":5,"comment":"indirimle uygun fiyatla ald\u0131m, kargo h\u0131zl\u0131","date":"10 \u015eubat 2022"},{"user":"canan b.","rate":5,"comment":"penyesi yeri \u00e7ok iyi","date":"5 \u015eubat 2022"},{"user":"E** A**","rate":5,"comment":"be\u011fenerek ald\u0131\u011f\u0131m Bi \u00fcr\u00fcnd\u00fcr kal\u0131b\u0131 da tam benlik g\u00fcven le alabilirsiniz","date":"4 May\u0131s 2022"},{"user":"S** D**","rate":3,"comment":"kalite yok ama g\u00f6mlek i\u00e7i falan ideal atlet gibi","date":"13 Nisan 2022"},{"user":"B** D**","rate":3,"comment":"Kalite olarak idare eder tam kal\u0131p kocama ald\u0131m pamuklanmad\u0131","date":"24 May\u0131s 2022"},{"user":"e** b**","rate":5,"comment":"Yaz \u0131c\u0131n guzel bir urun","date":"13 \u015eubat 2022"},{"user":"F** e** A**","rate":3,"comment":"D\u00fcmd\u00fcz ti\u015f\u00f6rt. G\u00fczel. Ama \u00f6n\u00fcnde siyah bi leke vard\u0131 ve tini ka\u00e7m\u0131\u015ft\u0131 ka\u00e7an ipi kestim makinede y\u0131kad\u0131m ge\u00e7ti leke fakat g\u00f6nderirken daha dikkatli olman\u0131z\u0131 tavsiye ederim say\u0131n trendyolman depo yetkilileri.","date":"12 Nisan 2022"},{"user":"S** \u00c7**","rate":5,"comment":"Erkek arkada\u015f\u0131ma ald\u0131m sala\u015f duruyor ama be\u011fendik","date":"11 \u015eubat 2022"},{"user":"S** B**","rate":5,"comment":"Tam kal\u0131p , rahat bi \u00fcr\u00fcn","date":"8 \u015eubat 2022"},{"user":"G** K**","rate":5,"comment":"G\u00fczeldi hediye olarak ald\u0131m","date":"13 \u015eubat 2022"},{"user":"M** \u00c7**","rate":4,"comment":"kalitesi g\u00fczel fakat kal\u0131plar bol kesim","date":"29 Nisan 2022"},{"user":"**** ****","rate":3,"comment":"Tam parlak beyaz de\u011fil, idare eder","date":"30 Nisan 2022"},{"user":"H** E**","rate":5,"comment":"Kal\u0131plar\u0131 cok g\u00fczel e\u015fim i\u00e7in ald\u0131m tam kal\u0131p","date":"1 \u015eubat 2022"},{"user":"e** l**","rate":5,"comment":"Penyesi kal\u0131b\u0131 g\u00fczel","date":"21 Nisan 2022"},{"user":"O** Y**","rate":3,"comment":"siradan geldi iade ettim","date":"22 Mart 2022"},{"user":"**** ****","rate":3,"comment":"Kalitesiz, iade","date":"25 Nisan 2022"},{"user":"P** A**","rate":5,"comment":"cok hafif kal\u0131b\u0131 cok g\u00fczel sala\u015f \u011fzernizde yok gibi al\u0131n ald\u0131r\u0131m \ud83d\ude00","date":"23 Nisan 2022"},{"user":"E** \u00d6**","rate":4,"comment":"Ya \u00fcr\u00fcn g\u00fczel ama atlet gibi de duruyo a\u00e7\u0131k\u00e7as\u0131. Kot pantolon ile \u00e7ok g\u00fczel oldu ama siyah pantolonla giyince sanki \u00fcst\u00fcne g\u00f6mlek de giymesi gerekiyor gibi duruyor. Alacaklar\u0131n bilgisine ben 55-60 aras\u0131 bi fiyata ald\u0131m daha \u00fcst\u00fc verilmez","date":"30 Nisan 2022"},{"user":"Y** C**","rate":5,"comment":"\u00dcr\u00fcn\u00fcn kalitesi fiyat\u0131na g\u00f6re gayet yerinde ve kesimleri \u00e7ok iyi","date":"22 \u015eubat 2022"},{"user":"g** k**","rate":2,"comment":"bu \u00fcr\u00fcn\u00fcn hem.siyahini hem beyaz\u0131n\u0131 ald\u0131k fakat beyaz olan\u0131 i\u00e7 g\u00f6steriyor atlet gibiydi","date":"7 Haziran 2022"},{"user":"\u00d6** B**","rate":1,"comment":"\u00dcr\u00fcn t-shirt de\u011fil de sanki fanila gibi. Maalesef be\u011fenmedim, iade edece\u011fim.","date":"26 Nisan 2022"},{"user":"**** ****","rate":2,"comment":"i\u00e7 g\u00f6steriyor","date":"7 Haziran 2022"},{"user":"m** g**","rate":4,"comment":"kuma\u015f\u0131 g\u00fczel fakat hafif i\u00e7 g\u00f6steriyor","date":"6 Haziran 2022"},{"user":"Onur V.","rate":5,"comment":"\u00dcr\u00fcn bol kal\u0131p rahat penyesi kaliteli","date":"11 \u015eubat 2022"},{"user":"O** K**","rate":4,"comment":"gri atlet biraz belli oluyor ama \u00fcr\u00fcn\u00fcn kalitesi g\u00fczel","date":"22 Nisan 2022"},{"user":"B** \u0130**","rate":5,"comment":"Karde\u015fime ald\u0131m i\u00e7 g\u00f6sterdi\u011fini bilerek ald\u0131k \ud83d\udc4d\ud83c\udffb","date":"22 Nisan 2022"},{"user":"M** \u015e**","rate":2,"comment":"\u0130\u00e7 g\u00f6steriyor be\u011fenmedik","date":"25 May\u0131s 2022"},{"user":"U** y** \u00d6**","rate":1,"comment":"Ti\u015f\u00f6rt elinden gelse i\u00e7 organlar\u0131n\u0131za kadar g\u00f6sterecek baya bir i\u00e7inizi g\u00f6steriyor kalitesiz sak\u0131n almay\u0131n","date":"14 Mart 2022"},{"user":"A** A** S**","rate":5,"comment":"Kuma\u015f\u0131 \u00e7ok g\u00fczel ve yumu\u015fak","date":"20 May\u0131s 2022"},{"user":"c** s**","rate":5,"comment":"\u00dcr\u00fcn gayet kaliteli. Tam bedeninizi al\u0131n.","date":"15 Nisan 2022"},{"user":"F** D**","rate":5,"comment":"Gayet iyi bir \u00fcr\u00fcn kuma\u015f\u0131 g\u00fczel tam yazl\u0131k","date":"25 Nisan 2022"},{"user":"N** \u00d6**","rate":3,"comment":"\u0130\u00e7 g\u00f6steriyor \u00e7ok kaliteli de\u011fil kazaklar\u0131m g\u00f6mleklerin i\u00e7ine giymelik","date":"27 \u015eubat 2022"},{"user":"F** S**","rate":5,"comment":"Kuma\u015f\u0131 \u00e7ok g\u00fczel. E\u015fime ald\u0131m \u00e7ok memnun kald\u0131k","date":"25 May\u0131s 2022"},{"user":"E** B**","rate":3,"comment":"i\u00e7 \u00e7ok belli ediyor, g\u00f6mlek i\u00e7ine giymelik","date":"19 Nisan 2022"},{"user":"H** N** E**","rate":5,"comment":"gayet guzel kurtarici urun. tam beden.","date":"11 May\u0131s 2022"},{"user":"M** A**","rate":5,"comment":"Rahat regular kuma\u015f\u0131 g\u00fczel","date":"18 May\u0131s 2022"},{"user":"T** T**","rate":5,"comment":"Biraz i\u00e7 g\u00f6steriyor onun d\u0131\u015f\u0131nda g\u00fczel","date":"24 May\u0131s 2022"},{"user":"batinuras_akkus","rate":5,"comment":"\u00dcr\u00fcn gayet g\u00fczel e\u015fim i\u00e7in ald\u0131k tam beden alabilirsiniz bu ay siyah\u0131n\u0131 da ald\u0131k hatta \ud83d\ude0a","date":"6 Nisan 2022"},{"user":"r** b**","rate":4,"comment":"yumu\u015fak yapida d\u00fcz ti\u015f\u00f6rt, ince. ben indirimden ald\u0131m norm fiyat\u0131 fazla bence","date":"16 Nisan 2022"},{"user":"**** ****","rate":3,"comment":"i\u00e7 g\u00f6steriyor, onun d\u0131\u015f\u0131nda g\u00fczel.","date":"28 Nisan 2022"},{"user":"E** K**","rate":3,"comment":"i\u00e7i g\u00f6steren bir ti\u015f\u00f6rt","date":"15 Nisan 2022"},{"user":"M** A**","rate":5,"comment":"ic g\u00f6steriyor fiyatina gore dandik","date":"20 May\u0131s 2022"},{"user":"H** Y**","rate":4,"comment":"\u00dcr\u00fcn gayet g\u00fczel yaln\u0131zca biraz i\u00e7 g\u00f6steriyor.","date":"24 May\u0131s 2022"},{"user":"T** O**","rate":3,"comment":"\u00fcr\u00fcn i\u00e7 g\u00f6steriyor.","date":"3 May\u0131s 2022"},{"user":"**** ****","rate":4,"comment":"i\u00e7 g\u00f6steriyor ama g\u00fczel yazl\u0131k hafif bir \u00fcr\u00fcn","date":"26 Nisan 2022"},{"user":"N** B**","rate":4,"comment":"\u0130\u00e7 g\u00f6steriyor ama yumu\u015fac\u0131k bu kadar fiyata al\u0131nmaz","date":"4 Nisan 2022"},{"user":"**** ****","rate":4,"comment":"kuma\u015f\u0131 yumu\u015fak ve g\u00fczel","date":"27 Nisan 2022"},{"user":"M** y**","rate":4,"comment":"kuma\u015f\u0131 g\u00fczel kendi bedeninizi al\u0131n","date":"14 May\u0131s 2022"},{"user":"E** A**","rate":5,"comment":"180 boy 89 kilo L beden tam oldu","date":"20 May\u0131s 2022"},{"user":"G** Y**","rate":2,"comment":"\u00dcr\u00fcn kuma\u015f\u0131 \u00e7ok k\u00f6t\u00fc yorumlara bAkarak aldm ama nas\u0131l be\u011fenildi\u011fine \u015fa\u015f\u0131rd\u0131m kald\u0131m.","date":"23 May\u0131s 2022"},{"user":"F** D**","rate":5,"comment":"\u00dcr\u00fcn cok g\u00fczel pamuklu yap\u0131s\u0131 var ben e\u015fime ald\u0131m cok severek kullanacak eminim","date":"15 Nisan 2022"},{"user":"**** ****","rate":5,"comment":"Kalite olarak g\u00fczel. 178 boy 93 kg L beden b\u00fcy\u00fck geldi. G\u00f6mlek alt\u0131na giymek i\u00e7in bu boy ve kilodakiler M beden alabilirler","date":"31 May\u0131s 2022"},{"user":"M** g**","rate":5,"comment":"kuma\u015f\u0131 yumu\u015fak g\u00fczel tam kal\u0131p","date":"27 Nisan 2022"},{"user":"r** a**","rate":4,"comment":"Orta derece bir tshirt","date":"30 Nisan 2022"},{"user":"ebruliimblog","rate":5,"comment":"3 rengini ald\u0131m e\u015fime. Kuma\u015f kalitesi \u00e7ok g\u00fczel \u00e7ok be\u011fendik te\u015fekk\u00fcrler :)","date":"21 Nisan 2022"},{"user":"S** \u015f**","rate":5,"comment":"kuma\u015f\u0131 g\u00fczeldi","date":"26 May\u0131s 2022"},{"user":"S** B**","rate":4,"comment":"kuma\u015f\u0131 \u00e7ok kal\u015fteli \u00e7\u0131kt\u0131","date":"7 May\u0131s 2022"},{"user":"K** T**","rate":5,"comment":"kuma\u015f\u0131 kaliteli \u00e7ok g\u00fczel","date":"6 May\u0131s 2022"},{"user":"m** g**","rate":5,"comment":"ba\u015far\u0131l\u0131 kaliteli bir kuma\u015f\u0131 var","date":"28 Nisan 2022"},{"user":"G** g**","rate":5,"comment":"Gayet kaliteli 88 kilo e\u015fim i\u00e7in L ald\u0131m biraz b\u00fcy\u00fck geldi M benden tam kal\u0131p olurdu","date":"29 May\u0131s 2022"},{"user":"**** ****","rate":5,"comment":"Erkek arkada\u015f\u0131ma ald\u0131m. 1.88 boyunda 95 kilo. XL ald\u0131m tam oldu. Kuma\u015f\u0131 kalitesi g\u00fczel.","date":"15 \u015eubat 2022"},{"user":"S** Y**","rate":5,"comment":"Kuma\u015f\u0131 dokusu gayet g\u00fczel. Al\u0131n\u0131r","date":"28 Nisan 2022"},{"user":"H** \u015e**","rate":5,"comment":"Kuma\u015f\u0131 \u00e7ok be\u011fendik","date":"22 Nisan 2022"},{"user":"A** K**","rate":5,"comment":"Kuma\u015f\u0131 harika e\u015fim bay\u0131ld\u0131","date":"10 Nisan 2022"},{"user":"a** y**","rate":5,"comment":"Karde\u015fime ald\u0131m g\u00fczel tam beden","date":"24 Nisan 2022"},{"user":"B** H**","rate":5,"comment":"Tam beden almal\u0131s\u0131n\u0131z","date":"13 Nisan 2022"},{"user":"F** B**","rate":5,"comment":"Kendi bedeninizi alabilirsiniz","date":"11 Nisan 2022"},{"user":"G** \u00c7**","rate":5,"comment":"gayet g\u00fczel sadece ben b\u00fcy\u00fck alm\u0131\u015f\u0131m \u263a\ufe0f","date":"30 Mart 2022"},{"user":"M** B**","rate":4,"comment":"G\u00fczel, resimdeki gibi. Tam beden","date":"21 Nisan 2022"},{"user":"**** ****","rate":3,"comment":"o\u011fluma ald\u0131m bildi\u011finiz ince atlet g\u00f6mlek i\u00e7i kullanicgi i\u00e7in pek umursamadim kalite eh i\u015fte diyelim","date":"31 May\u0131s 2022"},{"user":"\u00d6** E**","rate":1,"comment":"kesinlikle tavsiye etmiyorum. incecik ve kalitesiz kuma\u015f.","date":"21 May\u0131s 2022"},{"user":"osman \u015f.","rate":5,"comment":"Kaliteli kuma\u015f\u0131 var","date":"10 \u015eubat 2022"},{"user":"d** \u00f6**","rate":5,"comment":"E\u015fime ald\u0131m \u00e7ok be\u011fendi.\u00e7ok rahat tam beden","date":"18 May\u0131s 2022"},{"user":"**** ****","rate":5,"comment":"Kumasi kalitesi cok iyi parasini hak ediyor","date":"8 Nisan 2022"},{"user":"K** A**","rate":5,"comment":"Tam kal\u0131p pamuklu \u00fcr\u00fcn","date":"26 Nisan 2022"},{"user":"K** G** s**","rate":5,"comment":"kal\u0131b\u0131 \u00e7ok g\u00fczel e\u015fim 75 kilo m beden tam oldu","date":"27 May\u0131s 2022"},{"user":"s** d**","rate":5,"comment":"175 boy 80 kilo L beden tam oldu daha oturmas\u0131n\u0131 isteyenler M alabilir. dokusu yumu\u015fakl\u0131\u011f\u0131 \u00e7ok g\u00fczel kal\u0131b\u0131n\u0131 da be\u011fendik tavsiye ederim h\u0131zl\u0131 kargo","date":"25 Nisan 2022"},{"user":"S** A**","rate":5,"comment":"Kuma\u015f\u0131 kalitesi gayet iyi tam bedeninizi al\u0131n","date":"11 \u015eubat 2022"},{"user":"**** ****","rate":5,"comment":"M\u00fckemmel kuma\u015f\u0131 var tam beden al\u0131n","date":"16 Nisan 2022"},{"user":"**** ****","rate":4,"comment":"\u00dcr\u00fcn \u00e7ok g\u00fczel fakat bir beden k\u00fc\u00e7\u00fck al\u0131nmal\u0131 b\u00fcy\u00fck geldi","date":"5 May\u0131s 2022"},{"user":"S** Y**","rate":5,"comment":"kendi bedeninizi al\u0131n","date":"3 May\u0131s 2022"},{"user":"**** ****","rate":5,"comment":"G\u00fczel be\u011fendim bedeninizi alabilirsiniz . E\u015fime ald\u0131m oda be\u011fendi","date":"2 \u015eubat 2022"},{"user":"**** ****","rate":5,"comment":"kumasi guzel","date":"29 Mart 2022"},{"user":"Y** C** Y**","rate":4,"comment":"\u0130\u00e7 g\u00f6steriyor ama g\u00fczel","date":"10 \u015eubat 2022"},{"user":"H** N** \u00e7**","rate":5,"comment":"g\u00fczel kuma\u015f\u0131 var","date":"10 \u015eubat 2022"},{"user":"**** ****","rate":5,"comment":"kuma\u015f\u0131 \u00e7ok iyi xl ald\u0131m sala\u015f duruyor","date":"17 Nisan 2022"},{"user":"T** A**","rate":5,"comment":"E\u015fim i\u00e7in ald\u0131m , basic yeri pamuklu g\u00fczel ti\u015f\u00f6rt","date":"11 \u015eubat 2022"},{"user":"M** B**","rate":4,"comment":"rahat kal\u0131p bedeninizi alabilrsiniz","date":"26 Nisan 2022"},{"user":"T** G**","rate":3,"comment":"g\u00fczel basic tshirt i\u015fte ama 80 lira etmez","date":"6 Nisan 2022"},{"user":"C** \u015e**","rate":4,"comment":"Daha uygun f\u0131yata ald\u0131m, beden\u0131n\u0131z\u0131 alun","date":"22 \u015eubat 2022"},{"user":"meryem b.","rate":5,"comment":"\u00dcr\u00fcn gayet kaliteli fakat bir beden k\u00fc\u00e7\u00fck alinabilirmis","date":"22 \u015eubat 2022"},{"user":"M** \u00c7**","rate":5,"comment":"Kalitesi g\u00fczel tam bedeninizi alabilirsiniz","date":"14 \u015eubat 2022"},{"user":"A** a**","rate":5,"comment":"Tam bedenizi alin","date":"8 \u015eubat 2022"},{"user":"**** ****","rate":5,"comment":"Gaytte kaliteli kuma\u015f\u0131 var bence di\u011fer markalarda ayn\u0131 ama bu hem uygun hem g\u00fczel \ud83d\udc4d","date":"18 May\u0131s 2022"},{"user":"**** ****","rate":2,"comment":"2 renk ayn\u0131 beden sipari\u015f verdim beyaz olan bedeninden b\u00fcy\u00fck duruyordu","date":"23 May\u0131s 2022"},{"user":"H** B**","rate":5,"comment":"Kuma\u015f\u0131 \u00e7ok g\u00fczel sade \u015f\u0131k tam beden al\u0131nabilir","date":"10 \u015eubat 2022"},{"user":"A** P**","rate":1,"comment":"\u0130stedi\u011fim beden gelmedi \u00e7uval gibi \u015fey g\u00f6ndermi\u015fler","date":"25 Nisan 2022"},{"user":"S** C**","rate":5,"comment":"Erkek karde\u015fime alm\u0131\u015ft\u0131m ben giyiyorum \u00e7ok g\u00fczel bir kuma\u015f\u0131 var.","date":"29 Nisan 2022"},{"user":"y** d**","rate":5,"comment":"normal g\u00fcndelik bir kuma\u015fa sahip","date":"7 May\u0131s 2022"},{"user":"N** Y**","rate":3,"comment":"Herkesin yazd\u0131\u011f\u0131 kadar \u00e7ok kaliteli bir kuma\u015f de\u011fil idare eder","date":"28 May\u0131s 2022"},{"user":"A** \u00c7**","rate":5,"comment":"yazl\u0131k ince kullan\u0131\u015fl\u0131","date":"21 Nisan 2022"},{"user":"B** K**","rate":4,"comment":"Kuma\u015f\u0131 ince ancak yumu\u015fac\u0131k.be\u011fendim","date":"22 Nisan 2022"},{"user":"**** ****","rate":5,"comment":"E\u015fim i\u00e7in ald\u0131m. Kuma\u015f\u0131 ve rengi g\u00fczel. Be\u011fendik","date":"20 May\u0131s 2022"},{"user":"\u00fc** a**","rate":5,"comment":"tam renk beyaz, kaliteli kuma\u015f\u0131 var","date":"12 Nisan 2022"},{"user":"N** Y**","rate":2,"comment":"Cok ince bi kumasi var iade edicem","date":"31 May\u0131s 2022"},{"user":"M** A**","rate":2,"comment":"\u00dcr\u00fcn\u00fcn kalitesini pek begenemedim atlet gibi ince o y\u00fczden iade","date":"2 Nisan 2022"},{"user":"M** K**","rate":4,"comment":"179 boy 67 kilo L beden alabilirsiniz","date":"15 Nisan 2022"},{"user":"N** K**","rate":5,"comment":"kumasi gayet iyi sadece biraz fazla ince","date":"21 Nisan 2022"},{"user":"T** T**","rate":5,"comment":"duru\u015fu iyi  ama yaz\u0131n terledi\u011finde koku yapabilir %66 elastik kuma\u015f oldu\u011fundan","date":"24 Nisan 2022"},{"user":"N** G**","rate":5,"comment":"1.65 boy 52 kilo. S beden ald\u0131m. \u00dcr\u00fcn oversize durmas\u0131n ama \u00fczerime de yap\u0131\u015fmas\u0131n diyen k\u0131zlar teredd\u00fct etmeden alabilirsiniz","date":"22 \u015eubat 2022"},{"user":"Furkan A.","rate":5,"comment":"1.78 72 kg s beden gayet iyi 24 saatte teslim","date":"25 Nisan 2022"},{"user":"y** p**","rate":5,"comment":"kendi bedeninizi al\u0131n hafif bol g\u00fczel duruyor","date":"14 May\u0131s 2022"},{"user":"b** k**","rate":5,"comment":"178 80 alt\u0131 uzun geldi sadece","date":"21 Nisan 2022"},{"user":"Aytekin \u00f6.","rate":5,"comment":"Kuma\u015f ve model \u00e7ok iyi her zamanki markam.","date":"23 \u015eubat 2022"},{"user":"G** E**","rate":5,"comment":"Gayet g\u00fczel tam kal\u0131p kuma\u015f\u0131 da \u00e7ok iyi \ud83d\udc4d","date":"18 Mart 2022"},{"user":"**** ****","rate":2,"comment":"kumasi cok cok ince, atlet gibi. birkac yikamada yamulur. yine de hizli kargo icin 2 yildiz veriyorum","date":"10 May\u0131s 2022"},{"user":"M** Y**","rate":4,"comment":"176 boy 80 M beden g\u00fczel oldu S alsayd\u0131k yap\u0131\u015f\u0131rd\u0131","date":"31 Mart 2022"},{"user":"s** k**","rate":3,"comment":"Kuma\u015f\u0131 biraz ince ama uygun fiyatl\u0131 giyilebilir bir \u00fcr\u00fcn","date":"23 May\u0131s 2022"},{"user":"Burak Y.","rate":5,"comment":"XL beden ald\u0131\u011f\u0131m \u00fcr\u00fcn 180 cm 88 kiloyum rahat oldu L beden tam olur alanlara duyurulur \ud83d\udc4d\ud83c\udffd","date":"11 May\u0131s 2022"},{"user":"n** t**","rate":4,"comment":"erkek arkada\u015f\u0131ma g\u00f6mlek i\u00e7ine giymesi i\u00e7in ald\u0131m, 172 boy 80 kg L beden oldu kalitesi g\u00fczel","date":"10 May\u0131s 2022"},{"user":"S** \u00d6**","rate":4,"comment":"\u00fcr\u00fcn g\u00fczel fakat bekledi\u011fimden ince bi kuma\u015f\u0131 var.","date":"4 May\u0131s 2022"},{"user":"**** ****","rate":5,"comment":"kuma\u015f\u0131n\u0131 be\u011fendim. 181 boy 82 kilo L beden ald\u0131m hafif bol oldu.","date":"17 \u015eubat 2022"},{"user":"f** e**","rate":5,"comment":"\u00fcr\u00fcn\u00fcn t\u00fcm renklerinden ald\u0131k kuma\u015flar\u0131 harika geldi y\u0131kay\u0131nca cekme yapmad\u0131 tam beden alabilirsiniz","date":"13 May\u0131s 2022"},{"user":"E** D**","rate":5,"comment":"Kuma\u015f kaliteleri \u00e7ok g\u00fczel  178 boy 83 kilo L beden ald\u0131m tam oturmas\u0131n \u00fczerime diye  gayet istedi\u011fim beden oldu.","date":"23 Nisan 2022"},{"user":"**** ****","rate":2,"comment":"bu ti\u015f\u00f6rt biraz kalitesiz \u00e7ok ince kuma\u015f\u0131 var.","date":"28 Nisan 2022"},{"user":"F** k**","rate":5,"comment":"\u00c7ok g\u00fczel\ud83e\udd29 ke\u015fke kuma\u015f\u0131 ince olmasayd\u0131.","date":"22 Nisan 2022"},{"user":"Y** B**","rate":5,"comment":"Kalite kuma\u015f a\u015f\u0131r\u0131 h\u0131zl\u0131 kargo \ud83d\udc4d\ud83c\udffb","date":"8 Nisan 2022"},{"user":"\u0130** K**","rate":4,"comment":"Erkek arkadasim i\u00e7in ald\u0131m gunluk kullan\u0131m i\u00e7in uygun","date":"6 Nisan 2022"},{"user":"**** ****","rate":5,"comment":"1.79 boy 79 kilo m beden hafif bol oldu. slim fit sevenler s alabilirler","date":"23 Nisan 2022"},{"user":"E** K**","rate":1,"comment":"\u00fcr\u00fcn a\u015f\u0131r\u0131 kalitesiz a\u015f\u0131r\u0131 ince arkas\u0131 g\u00f6z\u00fck\u00fcyor resmen hi\u00e7 be\u011fenmedim kesinlikle tavsiye etmiyorum","date":"19 May\u0131s 2022"},{"user":"**** ****","rate":5,"comment":"Gayet g\u00fczel biraz geni\u015f oldu ama iade etmek istemedim","date":"9 May\u0131s 2022"},{"user":"O\u011fulcan A.","rate":3,"comment":"\u00dcr\u00fcn biraz ince ona g\u00f6re al\u0131n","date":"21 Nisan 2022"},{"user":"C** B**","rate":5,"comment":"\u00dcr\u00fcn gayet g\u00fczel kal\u0131b\u0131 k\u00fc\u00e7\u00fck de\u011fil kendi bedeninizi alabilirsiniz","date":"27 Nisan 2022"},{"user":"**** ****","rate":5,"comment":"sade bir ti\u015f\u00f6rt. sade, ince, elastik, fiyat\u0131na uygun kalitede. daha pahal\u0131 alsan\u0131z daha y\u00fcksek kalitede bir ti\u015f\u00f6rt bula bilirsinjz belki. puan\u0131m 5","date":"14 \u015eubat 2022"},{"user":"**** ****","rate":4,"comment":"Ayn\u0131 ti\u015f\u00f6rtten renk daha ald\u0131m fakat beyaz daha kalitesiz gibi","date":"25 Nisan 2022"},{"user":"G** B**","rate":2,"comment":"\u00c7ok ince kuma\u015f\u0131 yani alt\u0131na giyilen atleti belli edecek kadar.","date":"12 May\u0131s 2022"},{"user":"Kenan Y.","rate":5,"comment":"Boy 181-kilo 87 normal bir vucudum var L beden oldu. Kesim regular oldu\u011fu i\u00e7in fit bir vucudunuz varsa M alman\u0131z\u0131 \u00f6neririm","date":"21 Mart 2022"},{"user":"\u00d6** D**","rate":4,"comment":"kumas bekledigim gibi degildi esime aldim ama indirimden aldigim icin uyguna geldi iade yapmiycam","date":"22 Nisan 2022"},{"user":"k** t**","rate":5,"comment":"boydan uzun biraz onun d\u0131\u015f\u0131nda kuma\u015f\u0131 rengi vs gayet iyi","date":"26 May\u0131s 2022"},{"user":"\u0130** U**","rate":5,"comment":"Kalitesi g\u00fczel ama baya bolmu\u015f. Erkek arkada\u015f\u0131ma alm\u0131\u015ft\u0131m L \u00e7ok b\u00fcy\u00fck geldi mecbur iade ettim","date":"27 \u015eubat 2022"},{"user":"C** Z**","rate":3,"comment":"s\u00f6k\u00fck geldi boyun k\u0131sm\u0131, art\u0131k dikece\u011fiz geri g\u00f6ndermedim mali yumu\u015fac\u0131k","date":"21 Nisan 2022"},{"user":"B** G**","rate":4,"comment":"T shirt \u00e7ok g\u00fczel be\u011fendim yaln\u0131zca o kadar bekleyip defolu gelmesi sol kol omuz taraf\u0131nda tekstil par\u00e7as\u0131 olmas\u0131ndan dolay\u0131 1 puan k\u0131rd\u0131m","date":"8 Nisan 2022"},{"user":"A** \u00d6**","rate":4,"comment":"bir beden k\u00fc\u00e7\u00fck alman\u0131z tavsiye edilir uzun g\u00fczel \u00fcr\u00fcn","date":"9 Nisan 2022"},{"user":"E** B**","rate":3,"comment":"\u00c7ok i\u00e7 g\u00f6sterecek t\u00fcrden. Bedeni tam.","date":"15 \u015eubat 2022"},{"user":"B** S** A**","rate":3,"comment":"\u00dcr\u00fcn\u00fc pek be\u011fenmedim i\u00e7i g\u00f6steriyor ve dayanakl\u0131 bir kuma\u015f\u0131 yok gibi g\u00f6r\u00fcn\u00fcyor.","date":"15 Nisan 2022"},{"user":"D** A**","rate":3,"comment":"Tek olarak giymek i\u00e7in fazla ince ama yine de kalitesi k\u00f6t\u00fc de\u011fil","date":"11 Nisan 2022"},{"user":"n** y**","rate":1,"comment":"\u00e7ok ince atlet gibi iade ediyorum.","date":"13 May\u0131s 2022"},{"user":"Y** E**","rate":2,"comment":"\u00e7ok ince \u00f6nermem","date":"10 May\u0131s 2022"},{"user":"M** K**","rate":1,"comment":"a\u015f\u0131r\u0131 ince al\u0131nmaz almay\u0131n arkada\u015flar","date":"9 May\u0131s 2022"},{"user":"E** A**","rate":4,"comment":"\u00dcr\u00fcn ince ama giyilebilir yani","date":"25 Nisan 2022"},{"user":"\u00c7** K** S**","rate":3,"comment":"\u00c7ok ince kuma\u015f\u0131 di\u011fer renklerinden daha \u00e7ok memnun kald\u0131k","date":"29 Nisan 2022"},{"user":"i** \u00e7**","rate":4,"comment":"Kuma\u015f\u0131 g\u00fczel fakat \u00e7ok uzun geldi. 178 boy 78 kilo L beden alm\u0131\u015ft\u0131m","date":"18 May\u0131s 2022"},{"user":"D** E** T**","rate":5,"comment":"\u00dcr\u00fcn\u00fcn kuma\u015f\u0131 kesimi dikimi harika","date":"5 \u015eubat 2022"},{"user":"A** A**","rate":4,"comment":"\u00dcr\u00fcn h\u0131zl\u0131 bir \u015fekilde elime ula\u015ft\u0131 sadece biraz i\u00e7 g\u00f6steriyor ama fena de\u011fil","date":"22 Nisan 2022"},{"user":"E** V**","rate":1,"comment":"Ti\u015fortler birka\u00e7 tane e\u015fim i\u00e7in alm\u0131\u015ft\u0131m. inan\u0131lmaz kalitesiz ve incecik, baz\u0131lar\u0131n\u0131n rengi soluk  hi\u00e7 be\u011fenmedim, toz bezi gibi","date":"14 \u015eubat 2022"},{"user":"**** ****","rate":1,"comment":"\u00c7ok ince para verilip al\u0131nmaz","date":"27 Nisan 2022"},{"user":"g** e** a**","rate":3,"comment":"Kuma\u015f\u0131 ince en k\u00fc\u00e7\u00fck bedenini ald\u0131m ama yine bol sweatshirtlerin i\u00e7ine falan giyilir onun d\u0131\u015f\u0131nda \u00f6yle kaliteli bir duru\u015fu yok","date":"22 \u015eubat 2022"},{"user":"G** Y**","rate":5,"comment":"basic olarak kaliteli bir kumasi var y\u0131kad\u0131m sorun olmad\u0131 tavsiye ediyorum i\u00e7 de g\u00f6stermiyor","date":"1 Haziran 2022"},{"user":"S** D**","rate":5,"comment":"Kuma\u015f\u0131 \u00e7ok g\u00fczel i\u00e7 g\u00f6stermiyor tam beden alabilirsiniz","date":"6 May\u0131s 2022"},{"user":"n** i**","rate":3,"comment":"Daha \u00f6nceki aldigimla arasinda bariz kuma\u015f farki var. Bu gelen daha ince ve m bedene gore daha sala\u015f. e\u015fim cok begenmedi","date":"20 \u015eubat 2022"},{"user":"E** D**","rate":1,"comment":"Defolu geldi y\u0131rt\u0131kt\u0131, onun d\u0131\u015f\u0131nda ince fazlasiyla .","date":"7 May\u0131s 2022"},{"user":"**** ****","rate":1,"comment":"Daha \u00f6ncede beyaz tshirt alm\u0131\u015ft\u0131m ama kalitesi ayn\u0131 de\u011fil. \u0130\u00e7ini a\u015f\u0131r\u0131 belli ediyor","date":"22 Nisan 2022"},{"user":"S** G**","rate":5,"comment":"kal\u0131b\u0131 biraz b\u00fcy\u00fck ama \u00e7ok begendim","date":"27 Ocak 2022"},{"user":"F** T**","rate":5,"comment":"Sweatlar\u0131n alt\u0131ndan giymek i\u00e7in ald\u0131m ince ama fiyat\u0131na g\u00f6re iyi","date":"11 \u015eubat 2022"},{"user":"B** A**","rate":5,"comment":"Pamuklu yumu\u015fac\u0131k biraz ince i\u00e7 g\u00f6steriyo ama olsun be\u011fendik","date":"22 Nisan 2022"},{"user":"b\u00fc\u015franur \u0131.","rate":1,"comment":"YAKASI DEL\u0130K G\u00d6NDERD\u0130N\u0130Z ,PARAYI BEDAVA KAZANMIYORUZ. DAHA D\u0130KKATL\u0130 G\u00d6NDER\u0130N. DEFOLU MALA PARA VERMEK ZORUNDA DE\u011e\u0130L\u0130Z.","date":"13 Nisan 2022"},{"user":"E** Y**","rate":5,"comment":"Yuma\u015f\u0131c\u0131k penye kuma\u015f\u0131 var. Terletme yapm\u0131yor. Kal\u0131b\u0131 geni\u015f kal\u0131p .","date":"10 \u015eubat 2022"},{"user":"ya\u015far y.","rate":2,"comment":"kal\u0131b\u0131 bol ve ayn\u0131 yar\u0131m kollu atlet giymi\u015f gibi","date":"15 Nisan 2022"},{"user":"**** ****","rate":5,"comment":"ince beyaz bi ti\u015f\u00f6rt tam kal\u0131p","date":"15 Nisan 2022"},{"user":"**** ****","rate":4,"comment":"G\u00f6r\u00fcnd\u00fc\u011f\u00fc gibi g\u00fczel bi t\u0131k uzun","date":"26 \u015eubat 2022"},{"user":"C** Y**","rate":5,"comment":"Biraz ince fakat tam g\u00f6mlek alt\u0131na giymelik","date":"7 \u015eubat 2022"},{"user":"Y** Y** \u00c7**","rate":4,"comment":"Gayet g\u00fczel ama bir puan\u0131 kuma\u015f\u0131 i\u00e7in k\u0131rd\u0131m i\u00e7 g\u00f6steriyor biraz","date":"14 Mart 2022"},{"user":"**** ****","rate":5,"comment":"kuma\u015f\u0131 gayet g\u00fczel 190 cm 95 kilo xl beden indirimdeyken al\u0131n\u0131r","date":"9 Haziran 2022"},{"user":"**** ****","rate":3,"comment":"Guzel kuma\u015f\u0131 vard\u0131 ama beden\u0131 bol geld\u0131 o y\u00fczden \u0131ade ed\u0131yorum","date":"28 Nisan 2022"},{"user":"R** m** B**","rate":2,"comment":"\u00e7ok a\u015f\u0131r\u0131 ince v\u00fccut g\u00f6r\u00fcn\u00fcyor kalitesiz","date":"11 \u015eubat 2022"},{"user":"Y** V**","rate":5,"comment":"Karde\u015fim i\u00e7in ald\u0131k, kuma\u015f\u0131 \u00e7ok esnek ve kal\u0131n de\u011fil. Ama g\u00f6mlek i\u00e7ine giymelik alm\u0131\u015ft\u0131k, tam beyaz rengi","date":"13 \u015eubat 2022"},{"user":"**** ****","rate":4,"comment":"Kal\u0131p s\u00fcper biraz i\u00e7 g\u00f6steriyor","date":"28 May\u0131s 2022"},{"user":"G** U**","rate":4,"comment":"kuma\u015f olarak \u00e7ok g\u00fczel tam yazl\u0131k ic g\u00f6steriyor","date":"10 May\u0131s 2022"},{"user":"D** K**","rate":4,"comment":"guzel urun begendikk","date":"2 Haziran 2022"},{"user":"Feyyaz B.","rate":5,"comment":"\u00dcr\u00fcn hem uygun hem kaliteli \u00e7ok be\u011fendim","date":"9 Haziran 2022"},{"user":"c** a**","rate":3,"comment":"ayni urunden siyahini da almistim ikisinin kalibi farkli cikti iade ettim kaliplari biraz bol","date":"25 May\u0131s 2022"},{"user":"N** G**","rate":4,"comment":"biraz i\u00e7 belli ediyor tek s\u0131k\u0131nt\u0131s\u0131 o","date":"20 May\u0131s 2022"},{"user":"\u00d6** F** \u00c7**","rate":5,"comment":"Kuma\u015f\u0131 g\u00fczel tavsiye ederim","date":"18 May\u0131s 2022"},{"user":"E** E**","rate":4,"comment":"Bedeni tam ama ic g\u00f6steriyor","date":"29 Nisan 2022"},{"user":"G** K**","rate":3,"comment":"Cok uzun ve bol geld\u0131 s beden oyuzden iade","date":"11 Nisan 2022"},{"user":"A** A**","rate":5,"comment":"Gayet \u015f\u0131k ve rahat","date":"9 Haziran 2022"},{"user":"**** ****","rate":5,"comment":"Biraz i\u00e7 g\u00f6steriyor ama yine de g\u00fczel yumu\u015fak kuma\u015f\u0131 var","date":"30 May\u0131s 2022"},{"user":"\u015e** K**","rate":3,"comment":"Kuma\u015f\u0131 g\u00fczel ama maalesef i\u00e7 g\u00f6steriyor.","date":"11 May\u0131s 2022"},{"user":"E** Y** y**","rate":5,"comment":"Kaliteli \u00fct\u00fcn","date":"10 May\u0131s 2022"},{"user":"P** \u00d6**","rate":5,"comment":"\u00dcr\u00fcn \u00e7ok g\u00fczel herkese tavsiye ederim","date":"10 May\u0131s 2022"},{"user":"B** S**","rate":3,"comment":"Her rengini sipari\u015f verdim kuponlarla fiyat gayet g\u00fczel ama i\u00e7 g\u00f6steriyor beyaz atleti oldu\u011fu gibi meydanda a\u00e7\u0131k renklerde di\u011ferleri s\u00fcper","date":"14 May\u0131s 2022"},{"user":"F** A**","rate":1,"comment":"\u00c7ok ince kuma\u015f\u0131 be\u011fenemedim iade ettim","date":"8 Nisan 2022"},{"user":"h** y**","rate":5,"comment":"muhte\u015fem \u00fcr\u00fcn tesekk\u00fcrler trendyol","date":"21 May\u0131s 2022"},{"user":"b** c**","rate":2,"comment":"\u00c7ok ince kalitesiz duruyor iade","date":"27 Nisan 2022"},{"user":"**** ****","rate":4,"comment":"\u00c7ok ince olduk\u00e7a i\u00e7 g\u00f6steren bir kuma\u015f\u0131 var. Fakat ka\u00e7 kere y\u0131karsam y\u0131kayay\u0131m kuma\u015fta kendini b\u0131rakmak ya da renk de\u011fi\u015fikli\u011fi olmad\u0131","date":"11 May\u0131s 2022"},{"user":"**** ****","rate":5,"comment":"G\u00fczel \u00fcr\u00fcn kuma\u015f\u0131 da gayet kaliteli.","date":"25 Nisan 2022"},{"user":"\u0130** Z**","rate":2,"comment":"Bir tshirt i\u00e7in fazla ince geldi bana. \u0130\u00e7i bu kadar net g\u00f6stermemeli \ud83d\ude0c","date":"14 \u015eubat 2022"},{"user":"\u00c7** D**","rate":2,"comment":"ince \u00fcr\u00fcn i\u00e7 g\u00f6steriyor","date":"28 Ocak 2022"},{"user":"m** a**","rate":5,"comment":"kuma\u015f\u0131 kaliteli beden tam oldu","date":"22 Nisan 2022"},{"user":"S** Y**","rate":5,"comment":"\u00e7ok g\u00fczel hemen geldi \u00fcr\u00fcnler beklenildi\u011fi gibi","date":"7 May\u0131s 2022"},{"user":"**** ****","rate":4,"comment":"gayet g\u00fczel tavsiye edrim tam bedeninizi alin","date":"24 May\u0131s 2022"},{"user":"**** ****","rate":5,"comment":"\u00fcr\u00fcn g\u00f6r\u00fcnd\u00fc\u011f\u00fc gibi, \u00e7ok hafif i\u00e7 g\u00f6steriyor biraz ince bir kuma\u015f\u0131 var. tam bedeninizi alabilirsiniz","date":"7 Nisan 2022"},{"user":"e** d**","rate":4,"comment":"\u00dcr\u00fcn \u00e7ok ince ic g\u00f6steriyor ama tam bir yazl\u0131k","date":"10 Nisan 2022"},{"user":"S** T**","rate":3,"comment":"\u00c7ok ince. \u0130\u00e7 g\u00f6steriyor. Polyesteri fazla. Atletle giyilmez atletsiz yakar. Karars\u0131z\u0131m","date":"27 Nisan 2022"},{"user":"H** \u00c7**","rate":5,"comment":"Kuma\u015f\u0131 olduk\u00e7a g\u00fczel kuponla olduk\u00e7a indirimli oluyor. Bedeni de tam.","date":"28 Nisan 2022"},{"user":"c** d**","rate":2,"comment":"\u00c7ok ince epey i\u00e7 g\u00f6steriyor","date":"4 Nisan 2022"},{"user":"**** ****","rate":3,"comment":"\u00c7ok ince i\u00e7 g\u00f6steriyor","date":"2 Mart 2022"},{"user":"Taha Y.","rate":5,"comment":"harika tavsiye ederim \u00e7ok be\u011fendim te\u015fekk\u00fcrler","date":"8 May\u0131s 2022"},{"user":"k** k**","rate":4,"comment":"cok iyi bir \u00fcr\u00fcn","date":"30 Nisan 2022"},{"user":"\u0130** \u015e**","rate":4,"comment":"yumu\u015fac\u0131k, \u00e7ok g\u00fczel duruyor","date":"31 Mart 2022"},{"user":"Z** B** H**","rate":5,"comment":"tam bedeninize g\u00f6re al\u0131n","date":"28 May\u0131s 2022"},{"user":"D** K**","rate":3,"comment":"1.74 boy 75 kilo beyaz\u0131 \u00e7ok ince ic gosteriyor bide \u00e7ok uzun oldu","date":"21 Nisan 2022"},{"user":"**** ****","rate":4,"comment":"G\u00fczel \u00fcr\u00fcn","date":"17 Nisan 2022"},{"user":"Z** A**","rate":5,"comment":"Sevgilim i\u00e7in ald\u0131m ben be\u011fendim oda be\u011fenir in\u015fallah kargolama \u00f6zenliydi h\u0131zl\u0131 geldi","date":"16 \u015eubat 2022"},{"user":"A** M**","rate":5,"comment":"Ayn\u0131 resimdeki gibi.","date":"9 May\u0131s 2022"},{"user":"C** C**","rate":5,"comment":"kumas\u0131n\u0131 begend\u0131k uygun f\u0131yatl\u0131 gomlek \u0131cinr giyilebilir makul iyi b\u0131r \u00fcr\u00fcntam g\u00f6mlek i\u00e7i harika","date":"12 Nisan 2022"},{"user":"G** A**","rate":4,"comment":"Kuma\u015f\u0131 g\u00fczel ama ince biraz siyah\u0131n\u0131zda alm\u0131\u015ft\u0131k o daha g\u00fczel","date":"20 Nisan 2022"},{"user":"Z** K**","rate":5,"comment":"Kuma\u015f\u0131 gayet iyi, ince ve iril tiril.","date":"25 Nisan 2022"},{"user":"M** A**","rate":5,"comment":"E\u015fim i\u00e7in ald\u0131m tam yazl\u0131k efil efil dedikleri gibi evet biraz ince bi kuma\u015f\u0131 var","date":"26 Nisan 2022"},{"user":"h** a**","rate":1,"comment":"\u00fcr\u00fcn \u00e7ok ince ve i\u00e7inizi g\u00f6steriyor geri iade edece\u011fim alacak ki\u015filer buna dikkat etsin ev .i\u00e7inde giymek icin alinabilir ama d\u0131\u015far\u0131s\u0131 i\u00e7in g\u00fczel de\u011fil","date":"13 Nisan 2022"},{"user":"d** \u00e7**","rate":5,"comment":"e\u015fime ald\u0131m \u00e7ok be\u011fendi\ud83d\ude0a","date":"12 \u015eubat 2022"},{"user":"M** E**","rate":5,"comment":"Bu \u00fcr\u00fcn\u00fcn 3 rengini ald\u0131m  hediye olarak \u00e7ok g\u00fczel kal\u0131b\u0131 tam bedeninize gore al\u0131n","date":"21 Nisan 2022"},{"user":"B** B**","rate":4,"comment":"\u0130dare eder..","date":"25 Nisan 2022"},{"user":"\u0130lknur B.","rate":1,"comment":"S beden istiyip xxl g\u00f6ndermek ger\u00e7ekten hangi ak\u0131l mant\u0131\u011fa uygun bilmiyorum ama kalitesi a\u00e7\u0131s\u0131ndan ve tesett\u00fcrl\u00fc oldu\u011fum i\u00e7in geri iade etmeyece\u011fim bedenlere dikkat etseniz daha iyi olur.","date":"9 Nisan 2022"},{"user":"M** E**","rate":5,"comment":"E\u015fime ald\u0131m tam beden tam kal\u0131p","date":"1 Nisan 2022"},{"user":"Melis T.","rate":5,"comment":"G\u00fczel abim i\u00e7in ald\u0131m i\u00e7 g\u00f6steren bir kuma\u015f de\u011fil tavsiye ederim","date":"18 \u015eubat 2022"},{"user":"\u00d6** \u00c7**","rate":5,"comment":"\u00c7ok g\u00fczel penye ve kalitesi tam beden almal\u0131s\u0131n\u0131z","date":"6 \u015eubat 2022"},{"user":"E** D**","rate":5,"comment":"Kuma\u015f\u0131 kalitedi, kal\u0131b\u0131 gayet g\u00fczel ve d\u00fczg\u00fcn. Bedeninizi alman\u0131z\u0131 tavsiye ederim. Bu fiyata ka\u00e7maz.","date":"20 Nisan 2022"},{"user":"S** \u015f**","rate":3,"comment":"kuma\u015f\u0131 \u00e7ok ince etiketi kopuk geldi iade de edemedim. i\u00e7 g\u00f6steriyor","date":"17 Nisan 2022"},{"user":"r** Y**","rate":4,"comment":"Gayet g\u00fczel bir ti\u015f\u00f6rt ancak bekledi\u011fimden bir t\u0131k ince.","date":"7 \u015eubat 2022"},{"user":"H** Y**","rate":5,"comment":"Fiyat\u0131na g\u00f6re \u00e7ok \u00e7ok iyi","date":"10 \u015eubat 2022"},{"user":"evren u.","rate":5,"comment":"parasna g\u00f6re g\u00fczel \u00fcr\u00fcn pamuklu","date":"13 Mart 2022"},{"user":"n** s**","rate":5,"comment":"\u00e7ok be\u011fendim kazak i\u00e7ine giymek i\u00e7in alm\u0131\u015ft\u0131m \u00e7ok g\u00fczel","date":"2 \u015eubat 2022"},{"user":"S** \u015e**","rate":4,"comment":"Kuma\u015f\u0131 felan g\u00fczel ben indirimdeyken ald\u0131m sadece i\u00e7 g\u00f6steriyor. Kargo da h\u0131zl\u0131 geldi","date":"26 Mart 2022"},{"user":"K** A**","rate":5,"comment":"2 adet se\u00e7tim e\u015fimle kombin yapmak i\u00e7in bence kuma\u015flar\u0131 \u00e7ok iyi 2adet 80 TL ye ald\u0131m bence herkesin mutlaka dolab\u0131nda olmas\u0131 gereken bir par\u00e7a beden xl ald\u0131k sala\u015f sevdi\u011fimden dolay\u0131","date":"11 \u015eubat 2022"},{"user":"\u00d6** B**","rate":5,"comment":"Erkek karde\u015fim i\u00e7in ald\u0131k siyah & beyaz be\u011fendik \ud83c\udf38","date":"25 \u015eubat 2022"},{"user":"S** A**","rate":5,"comment":"Kuma\u015f\u0131 \u00e7ok iyi sadece bir t\u0131k kal\u0131plar\u0131 dar bence XXL ald\u0131m ama XL giyen birine tam olacak kadar.","date":"5 Nisan 2022"},{"user":"D** Y**","rate":3,"comment":"\u0130nce penye tarz\u0131 . G\u00f6mlek i\u00e7i yada sadece ti\u015f\u00f6rt olarak kullan\u0131labilir gayet g\u00fczel \u00fcr\u00fcn.","date":"4 Mart 2022"},{"user":"Semih A.","rate":4,"comment":"\u00dcr\u00fcn kaliteli ve g\u00fczel birazc\u0131k ince sadece ama kullan\u0131labilir","date":"12 \u015eubat 2022"},{"user":"**** ****","rate":3,"comment":"\u0130\u00e7 g\u00f6steriyor ve bedeninizden b\u00fcy\u00fck al\u0131n bence. Ama kargolama h\u0131zl\u0131yd\u0131 F\/P \u00fcr\u00fcn\u00fc fazlas\u0131n\u0131 hak etmez","date":"10 Nisan 2022"},{"user":"\u0130** A**","rate":1,"comment":"\u0130\u00e7 g\u00f6steriyor iade","date":"17 Nisan 2022"},{"user":"C** \u00d6**","rate":4,"comment":"Y\u0131kama sonras\u0131 \u00e7ekme pay\u0131n\u0131 d\u00fc\u015f\u00fcnerek XL beden ald\u0131m.\u0130nce bir kuma\u015f umar\u0131m bir s\u00fcre kullanabilirim.","date":"29 Ocak 2022"},{"user":"R** Y**","rate":1,"comment":"A\u015f\u0131r\u0131 ince i\u00e7 g\u00f6steriyor","date":"9 \u015eubat 2022"},{"user":"M** P**","rate":5,"comment":"Baya g\u00fczel","date":"14 Haziran 2022"},{"user":"M** T**","rate":5,"comment":"Kuma\u015f\u0131 yumu\u015fak g\u00fczel","date":"13 Haziran 2022"},{"user":"Y** G**","rate":5,"comment":"\u0130\u00e7 g\u00f6steriyor ama g\u00f6mlek i\u00e7ine giymek i\u00e7in g\u00fczel","date":"13 Haziran 2022"},{"user":"H** S**","rate":1,"comment":"\u00dcr\u00fcn\u00fcn kalitesi \u00e7ok k\u00f6t\u00fc incecik resmen iade","date":"13 Haziran 2022"},{"user":"E** A**","rate":5,"comment":"Pamuklu doku e\u015fim severek kullan\u0131yor \u00fc\u00e7 renk ald\u0131m","date":"11 Haziran 2022"},{"user":"S** B** K**","rate":3,"comment":"ikinci y\u0131kamadan sonra tiftiklenmeye ba\u015flad\u0131","date":"11 Haziran 2022"},{"user":"G** Y**","rate":5,"comment":"E\u015fime ald\u0131m \u00e7ok g\u00fczel oldu \u00fcst\u00fcne bedeninizi al\u0131n","date":"8 Haziran 2022"},{"user":"B** T**","rate":5,"comment":"Kuma\u015f\u0131 g\u00fczel","date":"8 Haziran 2022"},{"user":"Figen Y.","rate":2,"comment":"\u00fcr\u00fcn olduk\u00e7a ince i\u00e7 g\u00f6sterdi\u011fi i\u00e7in iade ettim","date":"6 Haziran 2022"},{"user":"esmaltnklc","rate":5,"comment":"Kuma\u015f\u0131 harika","date":"6 Haziran 2022"},{"user":"E** Y**","rate":4,"comment":"G\u00fczel al\u0131n\u0131t","date":"6 Haziran 2022"},{"user":"H** Y**","rate":3,"comment":"\u0130ndirim kuponuyla uygun fiyata geldi.Di\u011fer renklerinde hepsini ald\u0131m.Di\u011ferleri normal gezmelik tshirt gibi duruyor ama bu biraz fanila gibi duruyor.Meme u\u00e7lar\u0131n\u0131 ve g\u00f6\u011fs\u00fcn\u00fczdeki k\u0131llar\u0131 biraz belli ediyor.Dar beden giyerseniz k\u00f6t\u00fc durur.Bi beden b\u00fcy\u00fck alman\u0131z daha rahat giymenizi sa\u011flar.Ben tak\u0131m elbisenin i\u00e7ine giyerim diye ald\u0131m ama giyer miyim bilmiyorum.Denicem.Kuma\u015f\u0131n\u0131n polyester-pamuk kar\u0131\u015f\u0131m\u0131 olmas\u0131 bence bi avantaj.Bu tipteki %100 pamuk tshirtler \u00e7eki\u015ftirince veya y\u0131kad\u0131ktan sonra mutlaka bozulabiliyor.Polyester kar\u0131\u015f\u0131ml\u0131 kuma\u015flar kendini daha \u00e7abuk topluyor ve y\u0131kamaya kar\u015f\u0131 pamu\u011fa g\u00f6re biraz daha dirayetli.Diki\u015flerin nizamili\u011fi, kuma\u015f\u0131n kalitesi, v\u00fccutta duru\u015fu gayet g\u00fczel.Kuponla birlikte al\u0131n\u0131rsa f\/p \u00fcr\u00fcn\u00fc.","date":"5 Haziran 2022"},{"user":"FETH\u0130YE A.","rate":5,"comment":"erkek arkad\u015fa\u0131ma ald\u0131m g\u00fczel gayet","date":"4 Haziran 2022"},{"user":"\u00d6** \u0130**","rate":5,"comment":"Fitness  yap\u0131yorum 1.80'e 80'im, sporda giymek i\u00e7in ald\u0131m - M beden. ( Kollar s\u0131kabilir, terzide kestirdim )","date":"4 Haziran 2022"},{"user":"**** ****","rate":1,"comment":"lekeli \u00fcr\u00fcn g\u00f6nderdiler de\u011fi\u015fim yapmaya zaman\u0131m olmad\u0131\u011f\u0131 i\u00e7in \u00e7\u00f6p oldu","date":"2 Haziran 2022"},{"user":"\u00c7** O**","rate":5,"comment":"Fiyat performans \u00fcr\u00fcn\u00fc ger\u00e7ekten","date":"2 Haziran 2022"},{"user":"B** E**","rate":5,"comment":"fiyat\u0131na g\u00f6re iyi bir beden k\u00fc\u00e7\u00fck al\u0131nabilir","date":"1 Haziran 2022"},{"user":"z** y**","rate":5,"comment":"\u00e7ok be\u011fendim","date":"1 Haziran 2022"},{"user":"**** ****","rate":3,"comment":"kuma\u015f\u0131 \u00e7ok iyi de\u011fil","date":"1 Haziran 2022"}],"recommendations":[6018966,4032898,4032918,3866892,82975709,4032901,53677773,3866891,79866048,195500581,195500569,36353009,224555799,175743663,175318605,176826002,37355588,79866057,176776294,53677781],"cross":[186277008,35088074,35205829,35205832,35114554,35205830,36884780,35615745,35615743,90834015,198715748,35615744,83309218,32357905,176718033,38109865,31264146,31833025,87561320,35615741]}